z3c/pt/README.rst
z3c/pt/__init__.py
z3c/pt/configure.zcml
z3c/pt/expressions.py
z3c/pt/interfaces.py
z3c/pt/loader.py
z3c/pt/namespaces.py
z3c/pt/pagetemplate.py
z3c/pt/tests/__init__.py
z3c/pt/tests/boolean.pt
z3c/pt/tests/exists.pt
z3c/pt/tests/false.pt
z3c/pt/tests/function_namespaces.pt
z3c/pt/tests/helloworld.pt
z3c/pt/tests/nocall.pt
z3c/pt/tests/path.pt
z3c/pt/tests/provider.pt
z3c/pt/tests/test_doctests.py
z3c/pt/tests/test_expressions.py
z3c/pt/tests/test_interfaces.py
z3c/pt/tests/test_loader.py
z3c/pt/tests/test_namespaces.py
z3c/pt/tests/test_templates.py
z3c/pt/tests/view.pt
z3c_pt-5.0.dist-info/LICENSE.txt
z3c_pt-5.0.dist-info/METADATA
z3c_pt-5.0.dist-info/WHEEL
z3c_pt-5.0.dist-info/top_level.txt
z3c_pt-5.0.dist-info/RECORD
