Metadata-Version: 2.2
Name: z3c.pt
Version: 5.0
Summary: Fast ZPT engine.
Home-page: https://github.com/zopefoundation/z3c.pt
Author: Malthe Borch and the Zope Community
Author-email: zope-dev@zope.dev
License: ZPL
Project-URL: Sources, https://github.com/zopefoundation/z3c.pt
Project-URL: Issue Tracker, https://github.com/zopefoundation/z3c.pt/issues
Keywords: tal tales pagetemplate zope chameleon
Classifier: Development Status :: 5 - Production/Stable
Classifier: Environment :: Web Environment
Classifier: Intended Audience :: Developers
Classifier: License :: OSI Approved :: Zope Public License
Classifier: Programming Language :: Python :: 3
Classifier: Programming Language :: Python :: 3.9
Classifier: Programming Language :: Python :: 3.10
Classifier: Programming Language :: Python :: 3.11
Classifier: Programming Language :: Python :: 3.12
Classifier: Programming Language :: Python :: 3.13
Classifier: Programming Language :: Python :: Implementation :: CPython
Classifier: Programming Language :: Python :: Implementation :: PyPy
Classifier: Natural Language :: English
Classifier: Operating System :: OS Independent
Classifier: Topic :: Text Processing :: Markup :: HTML
Classifier: Topic :: Text Processing :: Markup :: XML
Classifier: Framework :: Zope :: 3
Requires-Python: >=3.9
License-File: LICENSE.txt
Requires-Dist: setuptools
Requires-Dist: zope.interface
Requires-Dist: zope.component
Requires-Dist: zope.i18n>=3.5
Requires-Dist: zope.traversing
Requires-Dist: zope.contentprovider
Requires-Dist: Chameleon>=2.4
Provides-Extra: test
Requires-Dist: zope.pagetemplate; extra == "test"
Requires-Dist: zope.testing; extra == "test"
Requires-Dist: zope.testrunner>=6.4; extra == "test"
Provides-Extra: docs
Requires-Dist: Sphinx; extra == "docs"
Dynamic: author
Dynamic: author-email
Dynamic: classifier
Dynamic: description
Dynamic: home-page
Dynamic: keywords
Dynamic: license
Dynamic: project-url
Dynamic: provides-extra
Dynamic: requires-dist
Dynamic: requires-python
Dynamic: summary
